furion/__init__.py
furion/config.py
furion/dns.py
furion/furion.py
furion/helpers.py
furion/ping.py
furion/servers.py
furion/simpleauth.py
furion/socks5.py
furion-1.5.3.dist-info/LICENSE
furion-1.5.3.dist-info/METADATA
furion-1.5.3.dist-info/WHEEL
furion-1.5.3.dist-info/entry_points.txt
furion-1.5.3.dist-info/top_level.txt
furion-1.5.3.dist-info/RECORD
