Metadata-Version: 2.1
Name: furion
Version: 1.5.3
Summary: A socks5 proxy with ssl support
Author-email: Keli Hu <dev@keli.hu>
License: MIT
Project-URL: Homepage, https://github.com/keli/furion
Keywords: socks5 proxy ssl
Requires-Python: >=3.8
License-File: LICENSE
Provides-Extra: dev
Requires-Dist: check-manifest; extra == "dev"
Provides-Extra: test
Requires-Dist: coverage; extra == "test"
